eehelper/__init__.py
eehelper/eehelper.py
eehelper-0.1.5.dist-info/DESCRIPTION.rst
eehelper-0.1.5.dist-info/METADATA
eehelper-0.1.5.dist-info/RECORD
eehelper-0.1.5.dist-info/WHEEL
eehelper-0.1.5.dist-info/metadata.json
eehelper-0.1.5.dist-info/top_level.txt
